SeleniumWebdriverJianyiJiaocheng/README.md
SeleniumWebdriverJianyiJiaocheng/__init__.py
SeleniumWebdriverJianyiJiaocheng/__main__.py
SeleniumWebdriverJianyiJiaocheng/file.epub
SeleniumWebdriverJianyiJiaocheng/index.html
SeleniumWebdriverJianyiJiaocheng/css/__init__.py
SeleniumWebdriverJianyiJiaocheng/css/annotations.css
SeleniumWebdriverJianyiJiaocheng/css/main.css
SeleniumWebdriverJianyiJiaocheng/css/normalize.css
SeleniumWebdriverJianyiJiaocheng/css/popup.css
SeleniumWebdriverJianyiJiaocheng/font/__init__.py
SeleniumWebdriverJianyiJiaocheng/font/fontello.eot
SeleniumWebdriverJianyiJiaocheng/font/fontello.svg
SeleniumWebdriverJianyiJiaocheng/font/fontello.ttf
SeleniumWebdriverJianyiJiaocheng/font/fontello.woff
SeleniumWebdriverJianyiJiaocheng/img/__init__.py
SeleniumWebdriverJianyiJiaocheng/img/annotator-glyph-sprite.png
SeleniumWebdriverJianyiJiaocheng/img/annotator-icon-sprite.png
SeleniumWebdriverJianyiJiaocheng/img/apple-touch-icon.png
SeleniumWebdriverJianyiJiaocheng/img/cancelfullscreen.png
SeleniumWebdriverJianyiJiaocheng/img/close.png
SeleniumWebdriverJianyiJiaocheng/img/fullscreen.png
SeleniumWebdriverJianyiJiaocheng/img/loader.gif
SeleniumWebdriverJianyiJiaocheng/img/menu-icon.png
SeleniumWebdriverJianyiJiaocheng/img/save.png
SeleniumWebdriverJianyiJiaocheng/img/saved.png
SeleniumWebdriverJianyiJiaocheng/img/settings-s.png
SeleniumWebdriverJianyiJiaocheng/img/settings.png
SeleniumWebdriverJianyiJiaocheng/img/star.png
SeleniumWebdriverJianyiJiaocheng/js/__init__.py
SeleniumWebdriverJianyiJiaocheng/js/epub.js
SeleniumWebdriverJianyiJiaocheng/js/epub.min.js
SeleniumWebdriverJianyiJiaocheng/js/epub.min.map
SeleniumWebdriverJianyiJiaocheng/js/hooks.min.js
SeleniumWebdriverJianyiJiaocheng/js/hooks.min.map
SeleniumWebdriverJianyiJiaocheng/js/reader.js
SeleniumWebdriverJianyiJiaocheng/js/reader.js.map
SeleniumWebdriverJianyiJiaocheng/js/reader.min.js
SeleniumWebdriverJianyiJiaocheng/js/reader.min.map
SeleniumWebdriverJianyiJiaocheng/js/hooks/__init__.py
selenium_webdriver_jianyi_jiaocheng-2024.3.1.0.dist-info/METADATA
selenium_webdriver_jianyi_jiaocheng-2024.3.1.0.dist-info/WHEEL
selenium_webdriver_jianyi_jiaocheng-2024.3.1.0.dist-info/entry_points.txt
selenium_webdriver_jianyi_jiaocheng-2024.3.1.0.dist-info/top_level.txt
selenium_webdriver_jianyi_jiaocheng-2024.3.1.0.dist-info/RECORD
